setup.py
trlo.py
trlo.egg-info/PKG-INFO
trlo.egg-info/SOURCES.txt
trlo.egg-info/dependency_links.txt
trlo.egg-info/requires.txt
trlo.egg-info/top_level.txt