Metadata-Version: 1.1
Name: trlo
Version: 1.0
Summary: A minimalist Trello API client.
Home-page: http://github.com/jacobian/trlo
Author: Jacob Kaplan-Moss
Author-email: jacob@jacobian.org
License: UNKNOWN
Platform: UNKNOWN
Classifier: Development Status :: 4 - Beta
Classifier: Intended Audience :: Developers
Classifier: License :: OSI Approved :: BSD License
Classifier: Programming Language :: Python :: 2.7
Classifier: Topic :: Internet :: WWW/HTTP
